{
  "publicPath": "/_nuxt/",
  "all": [
    "4.nuxt.bundle.d50e6c7e0ac5fc9cdd6d.js",
    "img/fontawesome-webfont.912ec66.svg",
    "fonts/fontawesome-webfont.b06871f.ttf",
    "fonts/fontawesome-webfont.af7ae50.woff2",
    "fonts/fontawesome-webfont.fee66e7.woff",
    "img/headshot.e564bed.jpg",
    "0.nuxt.bundle.7ca06712d430fc82be9d.js",
    "1.nuxt.bundle.45f13198c4db0c294685.js",
    "2.nuxt.bundle.f5e6033c8ff42912f43d.js",
    "3.nuxt.bundle.d2591ab175a00e1ef829.js",
    "fonts/fontawesome-webfont.674f50d.eot",
    "5.nuxt.bundle.407d0df68b1e402d93b8.js",
    "6.nuxt.bundle.bc6b4f3fd0ad1b279e35.js",
    "vendor.bundle.18c964c558a3d08648f8.js",
    "nuxt.bundle.72408270caed29efc400.js",
    "9.nuxt.bundle.aae141b27dc803c55286.js",
    "10.nuxt.bundle.3989c2c23a4e70529935.js",
    "11.nuxt.bundle.2281fea4c11d4a4ff397.js",
    "12.nuxt.bundle.9a0e2bf70da42ebe1a1a.js",
    "manifest.4dd1c4b95b72d8da06d3.js",
    "index.html"
  ],
  "initial": [
    "manifest.4dd1c4b95b72d8da06d3.js",
    "vendor.bundle.18c964c558a3d08648f8.js",
    "nuxt.bundle.72408270caed29efc400.js"
  ],
  "async": [
    "4.nuxt.bundle.d50e6c7e0ac5fc9cdd6d.js",
    "0.nuxt.bundle.7ca06712d430fc82be9d.js",
    "1.nuxt.bundle.45f13198c4db0c294685.js",
    "2.nuxt.bundle.f5e6033c8ff42912f43d.js",
    "3.nuxt.bundle.d2591ab175a00e1ef829.js",
    "5.nuxt.bundle.407d0df68b1e402d93b8.js",
    "6.nuxt.bundle.bc6b4f3fd0ad1b279e35.js",
    "9.nuxt.bundle.aae141b27dc803c55286.js",
    "10.nuxt.bundle.3989c2c23a4e70529935.js",
    "11.nuxt.bundle.2281fea4c11d4a4ff397.js",
    "12.nuxt.bundle.9a0e2bf70da42ebe1a1a.js"
  ],
  "modules": {
    "12295838": [
      13,
      1,
      10,
      10,
      2,
      3,
      4
    ],
    "29258737": [
      8
    ],
    "34175488": [
      8
    ],
    "44312662": [
      6
    ],
    "59607317": [
      6
    ],
    "70871162": [
      6
    ],
    "76327357": [
      13,
      1,
      10,
      10,
      2,
      3,
      4
    ],
    "c01c3ba4": [
      13,
      1,
      10,
      10,
      2,
      3,
      4
    ],
    "432b2c02": [
      13,
      1,
      10,
      10,
      2,
      3,
      4
    ],
    "c5086204": [
      13,
      1,
      10,
      10,
      2,
      3,
      4
    ],
    "481acabe": [
      13,
      1,
      10,
      10,
      2,
      3,
      4
    ],
    "6e74b0ee": [
      13,
      1,
      10,
      10,
      2,
      3,
      4
    ],
    "a730696e": [
      13,
      1,
      10,
      10,
      2,
      3,
      4
    ],
    "f467745a": [
      13,
      1,
      10,
      10,
      2,
      3,
      4
    ],
    "40a7f77f": [
      13,
      1,
      10,
      10,
      2,
      3,
      4
    ],
    "63a35a13": [
      13,
      1,
      10,
      10,
      2,
      3,
      4
    ],
    "954745aa": [
      13,
      1,
      10,
      10,
      2,
      3,
      4
    ],
    "666c1ff8": [
      13,
      1,
      10,
      10,
      2,
      3,
      4
    ],
    "6bdf75ab": [
      13,
      1,
      10,
      10,
      2,
      3,
      4
    ],
    "542ae743": [
      13,
      1,
      10,
      10,
      2,
      3,
      4
    ],
    "a9991bd6": [
      13,
      1,
      10,
      10,
      2,
      3,
      4
    ],
    "5ab31352": [
      13,
      1,
      10,
      10,
      2,
      3,
      4
    ],
    "7e036af3": [
      13,
      1,
      10,
      10,
      2,
      3,
      4
    ],
    "c0ed0d66": [
      13,
      1,
      10,
      10,
      2,
      3,
      4
    ],
    "d70d4caa": [
      13,
      1,
      10,
      10,
      2,
      3,
      4
    ],
    "113c9e48": [
      13,
      1,
      10,
      10,
      2,
      3,
      4
    ],
    "4e1d2b10": [
      13,
      1,
      10,
      10,
      2,
      3,
      4
    ],
    "712f143e": [
      13,
      1,
      10,
      10,
      2,
      3,
      4
    ],
    "7e520f26": [
      13,
      1,
      10,
      10,
      2,
      3,
      4
    ],
    "230a2912": [
      13,
      1,
      10,
      10,
      2,
      3,
      4
    ],
    "24f789c3": [
      13,
      1,
      10,
      10,
      2,
      3,
      4
    ],
    "90e519f8": [
      13,
      1,
      10,
      10,
      2,
      3,
      4
    ],
    "1952edc8": [
      13,
      1,
      10,
      10,
      2,
      3,
      4
    ],
    "c7359f46": [
      13,
      1,
      10,
      10,
      2,
      3,
      4
    ],
    "5bd2b8b3": [
      13,
      1,
      10,
      10,
      2,
      3,
      4
    ],
    "6c90f6e2": [
      13,
      1,
      10,
      10,
      2,
      3,
      4
    ],
    "db5d6e7a": [
      13,
      1,
      10,
      10,
      2,
      3,
      4
    ],
    "108232df": [
      13,
      1,
      10,
      10,
      2,
      3,
      4
    ],
    "e76fab86": [
      13,
      1,
      10,
      10,
      2,
      3,
      4
    ],
    "0887c504": [
      13,
      1,
      10,
      10,
      2,
      3,
      4
    ],
    "4195ef3a": [
      13,
      1,
      10,
      10,
      2,
      3,
      4
    ],
    "1b7ea394": [
      13,
      1,
      10,
      10,
      2,
      3,
      4
    ],
    "ae4fa958": [
      13,
      1,
      10,
      10,
      2,
      3,
      4
    ],
    "4ac6efac": [
      13,
      1,
      10,
      10,
      2,
      3,
      4
    ],
    "281756fc": [
      13,
      1,
      10,
      10,
      2,
      3,
      4
    ],
    "69f2e515": [
      13,
      1,
      10,
      10,
      2,
      3,
      4
    ],
    "d4eeac88": [
      13,
      1,
      10,
      10,
      2,
      3,
      4
    ],
    "430f75cc": [
      13,
      1,
      10,
      10,
      2,
      3,
      4
    ],
    "381abe90": [
      13,
      1,
      10,
      10,
      2,
      3,
      4
    ],
    "75c68f5a": [
      13,
      1,
      10,
      10,
      2,
      3,
      4
    ],
    "1c7f8a5b": [
      13,
      1,
      10,
      10,
      2,
      3,
      4
    ],
    "02de2fd4": [
      13,
      1,
      10,
      10,
      2,
      3,
      4
    ],
    "6920144e": [
      14
    ],
    "1174b76d": [
      13,
      1,
      10,
      10,
      2,
      3,
      4
    ],
    "2bb07e1a": [
      13,
      1,
      10,
      10,
      2,
      3,
      4
    ],
    "f48ce392": [
      13,
      1,
      10,
      10,
      2,
      3,
      4
    ],
    "533b6412": [
      13,
      1,
      10,
      10,
      2,
      3,
      4
    ],
    "fe5d4758": [
      14
    ],
    "2b14d6eb": [
      13,
      1,
      10,
      10,
      2,
      3,
      4
    ],
    "34cbdbfe": [
      13,
      1,
      10,
      10,
      2,
      3,
      4
    ],
    "53ef4876": [
      13,
      1,
      10,
      10,
      2,
      3,
      4
    ],
    "214908ac": [
      13,
      1,
      10,
      10,
      2,
      3,
      4
    ],
    "1e9451c5": [
      13,
      1,
      10,
      10,
      2,
      3,
      4
    ],
    "3a37e89d": [
      13,
      1,
      10,
      10,
      2,
      3,
      4
    ],
    "5947dba3": [
      13,
      1,
      10,
      10,
      2,
      3,
      4
    ],
    "ae54350e": [
      13,
      1,
      10,
      10,
      2,
      3,
      4
    ],
    "555a5e99": [
      13,
      1,
      10,
      10,
      2,
      3,
      4
    ],
    "75a8bada": [
      13,
      1,
      10,
      10,
      2,
      3,
      4
    ],
    "a2bbd748": [
      13,
      1,
      10,
      10,
      2,
      3,
      4
    ],
    "2f68c696": [
      13,
      1,
      10,
      10,
      2,
      3,
      4
    ],
    "470793f4": [
      13,
      1,
      10,
      10,
      2,
      3,
      4
    ],
    "669d4c98": [
      13,
      1,
      10,
      10,
      2,
      3,
      4
    ],
    "20ed8a18": [
      14
    ],
    "4443fc8d": [
      14
    ],
    "7859937d": [
      14
    ],
    "12cd582a": [
      14
    ],
    "02efcea4": [
      14
    ],
    "e0b560b8": [
      14
    ],
    "fd876c54": [
      14
    ],
    "7e799266": [
      14
    ],
    "b82e03c4": [
      14
    ],
    "17d11f76": [
      14
    ],
    "7f6c6c46": [
      14
    ],
    "99ca2ec2": [
      14
    ],
    "8e838d16": [
      14
    ],
    "0f26a52e": [
      14
    ],
    "3bb9ba7a": [
      14
    ],
    "7eae1f28": [
      13,
      1,
      10,
      10,
      2,
      3,
      4
    ],
    "5365650c": [
      13,
      1,
      10,
      10,
      2,
      3,
      4
    ],
    "0a742bce": [
      13,
      1,
      10,
      10,
      2,
      3,
      4
    ],
    "4928a10c": [
      13,
      1,
      10,
      10,
      2,
      3,
      4
    ],
    "ae1a9366": [
      13,
      1,
      10,
      10,
      2,
      3,
      4
    ],
    "9630a644": [
      13,
      1,
      10,
      10,
      2,
      3,
      4
    ],
    "c511898e": [
      13,
      1,
      10,
      10,
      2,
      3,
      4
    ],
    "28b78c82": [
      13,
      1,
      10,
      10,
      2,
      3,
      4
    ],
    "8ef14694": [
      13,
      1,
      10,
      10,
      2,
      3,
      4
    ],
    "1bb4e058": [
      13,
      1,
      10,
      10,
      2,
      3,
      4
    ],
    "7bf34590": [
      13,
      1,
      10,
      10,
      2,
      3,
      4
    ],
    "7598ea58": [
      13,
      1,
      10,
      10,
      2,
      3,
      4
    ],
    "92c3853c": [
      13,
      1,
      10,
      10,
      2,
      3,
      4
    ],
    "64508a26": [
      13,
      1,
      10,
      10,
      2,
      3,
      4
    ],
    "f4416374": [
      13,
      1,
      10,
      10,
      2,
      3,
      4
    ],
    "1ecb6209": [
      13,
      1,
      10,
      10,
      2,
      3,
      4
    ],
    "157bd23e": [
      13,
      1,
      10,
      10,
      2,
      3,
      4
    ],
    "1735716a": [
      13,
      1,
      10,
      10,
      2,
      3,
      4
    ],
    "5bf9fd5a": [
      13,
      1,
      10,
      10,
      2,
      3,
      4
    ],
    "abab6488": [
      13,
      1,
      10,
      10,
      2,
      3,
      4
    ],
    "176792b5": [
      13,
      1,
      10,
      10,
      2,
      3,
      4
    ],
    "6b2e1ba8": [
      13,
      1,
      10,
      10,
      2,
      3,
      4
    ],
    "5cdcd4f7": [
      13,
      1,
      10,
      10,
      2,
      3,
      4
    ],
    "433363dc": [
      13,
      1,
      10,
      10,
      2,
      3,
      4
    ],
    "7813b344": [
      13,
      1,
      10,
      10,
      2,
      3,
      4
    ],
    "eba9da60": [
      13,
      1,
      10,
      10,
      2,
      3,
      4
    ],
    "10e66408": [
      13,
      1,
      10,
      10,
      2,
      3,
      4
    ],
    "ae5d4c7a": [
      13,
      1,
      10,
      10,
      2,
      3,
      4
    ],
    "c9dc15b6": [
      13,
      1,
      10,
      10,
      2,
      3,
      4
    ],
    "16031c69": [
      13,
      1,
      10,
      10,
      2,
      3,
      4
    ],
    "29aa57ad": [
      13,
      1,
      10,
      10,
      2,
      3,
      4
    ],
    "33a11482": [
      13,
      1,
      10,
      10,
      2,
      3,
      4
    ],
    "f5d03788": [
      13,
      1,
      10,
      10,
      2,
      3,
      4
    ],
    "7a9ea524": [
      13,
      1,
      10,
      10,
      2,
      3,
      4
    ],
    "96a18744": [
      13,
      1,
      10,
      10,
      2,
      3,
      4
    ],
    "465087fe": [
      13,
      1,
      10,
      10,
      2,
      3,
      4
    ],
    "7b2e604c": [
      13,
      1,
      10,
      10,
      2,
      3,
      4
    ],
    "302952e5": [
      13,
      1,
      10,
      10,
      2,
      3,
      4
    ],
    "03d31468": [
      13,
      1,
      10,
      10,
      2,
      3,
      4
    ],
    "5b6a057a": [
      13,
      1,
      10,
      10,
      2,
      3,
      4
    ],
    "480257eb": [
      13,
      1,
      10,
      10,
      2,
      3,
      4
    ],
    "32cd3290": [
      13,
      1,
      10,
      10,
      2,
      3,
      4
    ],
    "3d9703f0": [
      13,
      1,
      10,
      10,
      2,
      3,
      4
    ],
    "dbb12668": [
      13,
      1,
      10,
      10,
      2,
      3,
      4
    ],
    "56af0bf4": [
      14
    ],
    "6eef0ce2": [
      14
    ],
    "4b9cd292": [
      14
    ],
    "229ebb80": [
      14
    ],
    "5ea4b3e6": [
      14
    ],
    "5f92ff5d": [
      13,
      1,
      10,
      10,
      2,
      3,
      4
    ],
    "1800b5f8": [
      13,
      1,
      10,
      10,
      2,
      3,
      4
    ],
    "13bf7be0": [
      13,
      1,
      10,
      10,
      2,
      3,
      4
    ],
    "4c78bce4": [
      13,
      1,
      10,
      10,
      2,
      3,
      4
    ],
    "0c1bafc7": [
      13,
      1,
      10,
      10,
      2,
      3,
      4
    ],
    "6f334ca3": [
      13,
      1,
      10,
      10,
      2,
      3,
      4
    ],
    "7c613466": [
      13,
      1,
      10,
      10,
      2,
      3,
      4
    ],
    "c75da7fc": [
      14
    ],
    "120a614c": [
      14
    ],
    "e961fd46": [
      14
    ],
    "4e593222": [
      14
    ],
    "5c7b9195": [
      14
    ],
    "49ce1db2": [
      14
    ],
    "6d023bcb": [
      14
    ],
    "2133ffe6": [
      14
    ],
    "0a6acac2": [
      14
    ],
    "e0beb652": [
      14
    ],
    "bc8f5d40": [
      14
    ],
    "7db051c6": [
      14
    ],
    "5be7f1a4": [
      13,
      1,
      10,
      10,
      2,
      3,
      4
    ],
    "2d27b1f9": [
      14
    ],
    "629e580d": [
      13,
      1,
      10,
      10,
      2,
      3,
      4
    ],
    "ef33174c": [
      8
    ],
    "6b092521": [
      9,
      5
    ],
    "605d9598": [
      12
    ],
    "ea7e0034": [
      7
    ],
    "75ee95b9": [
      11
    ],
    "5f784260": [
      0
    ],
    "669bb2c5": [
      6
    ],
    "5df20626": [
      6
    ],
    "22cf5b7a": [
      6
    ],
    "064c5bec": [
      6
    ],
    "47de20af": [
      6
    ],
    "593cefb2": [
      6
    ],
    "fc9c9826": [
      6
    ],
    "335434f1": [
      6
    ],
    "3875003c": [
      6
    ],
    "ddaa71bc": [
      6
    ],
    "55e040f9": [
      6
    ],
    "06a2c060": [
      8
    ],
    "1de103c2": [
      8
    ],
    "bdb5d422": [
      8
    ],
    "c93e7876": [
      8
    ],
    "1353a304": [
      9,
      5
    ],
    "87fd495e": [
      12
    ],
    "160e0943": [
      7
    ],
    "9d121402": [
      6
    ],
    "16ada896": [
      11
    ],
    "7102f1ad": [
      0
    ],
    "0123cdec": [
      0
    ],
    "6a091c50": [
      8
    ],
    "07fbaa9d": [
      8
    ],
    "7ab7f445": [
      9,
      5
    ],
    "4e8c8a23": [
      6
    ],
    "de4ac2a6": [
      12
    ],
    "d1792eaa": [
      7
    ],
    "19ef5678": [
      8
    ],
    "656ef2b0": [
      8
    ],
    "6dc9ec54": [
      11
    ],
    "6a688a17": [
      8
    ],
    "a0c08154": [
      6
    ],
    "9fd2a822": [
      18
    ],
    "9fd1bf64": [
      17
    ],
    "9fd0d6a6": [
      16
    ],
    "5ddf98ee": [
      6
    ],
    "402f13b6": [
      6
    ],
    "7dbf8a00": [
      6
    ],
    "2ace4208": [
      6
    ],
    "1ec21414": [
      6
    ],
    "643fb39a": [
      6
    ],
    "1822c90d": [
      6
    ],
    "1d74bb29": [
      6
    ],
    "3717c8ca": [
      6
    ],
    "2593cc36": [
      6
    ],
    "7411f206": [
      6
    ],
    "02fb4c83": [
      6
    ],
    "3e07899f": [
      6
    ],
    "71f8fe36": [
      6
    ],
    "70b4c02f": [
      6
    ],
    "723eec0e": [
      6
    ],
    "5b0c9a1b": [
      6
    ],
    "3e384515": [
      6
    ],
    "729c19e4": [
      6
    ],
    "2854a21e": [
      6
    ],
    "21dfb0cf": [
      6
    ],
    "1a38bed2": [
      6
    ],
    "2dc1cdca": [
      6
    ],
    "c1771190": [
      6
    ],
    "87654f8a": [
      6
    ],
    "7d0113e7": [
      6
    ],
    "04f47858": [
      6
    ],
    "5477a126": [
      6
    ],
    "2c2fe7fb": [
      6
    ],
    "faedbb50": [
      6
    ],
    "72723b6d": [
      6
    ],
    "2b0b5733": [
      6
    ],
    "4ce1785a": [
      6
    ],
    "30f5d907": [
      6
    ],
    "05468be5": [
      6
    ],
    "a862185e": [
      6
    ],
    "8a5f23ac": [
      6
    ],
    "1a1e14aa": [
      6
    ],
    "6924ac4d": [
      6
    ],
    "68a1b113": [
      6
    ],
    "11e45536": [
      6
    ],
    "2a3b6018": [
      6
    ],
    "e32e4f68": [
      6
    ],
    "0b163bc7": [
      6
    ],
    "e85c6c3e": [
      6
    ],
    "5402f0c1": [
      6
    ],
    "f3cba486": [
      6
    ],
    "7d6d9ed6": [
      6
    ],
    "5941c1d8": [
      6
    ],
    "736beb70": [
      6
    ],
    "72f6035d": [
      6
    ],
    "7ebc5982": [
      6
    ],
    "a02f368a": [
      6
    ],
    "b6c6c2e8": [
      9,
      5
    ],
    "e12e5f9a": [
      8
    ],
    "9ec997b6": [
      8
    ],
    "00660312": [
      8
    ],
    "2e1af428": [
      8
    ],
    "ad6d6636": [
      0
    ],
    "64fe6d6b": [
      8
    ],
    "1b4b6a78": [
      8
    ],
    "4423c5a0": [
      9,
      5
    ],
    "4017c73e": [
      6
    ],
    "e6917d70": [
      12
    ],
    "5e18f3f4": [
      7
    ],
    "83cbd828": [
      8
    ],
    "3e73487a": [
      8
    ],
    "43cb27a2": [
      11
    ],
    "141fab32": [
      8
    ],
    "3d56deea": [
      0
    ],
    "5e502ba0": [
      8
    ],
    "45e4707d": [
      8
    ],
    "bea2abb6": [
      9,
      5
    ],
    "95494ffa": [
      6
    ],
    "13fb5c8d": [
      12
    ],
    "858bc2ea": [
      7
    ],
    "6fdcaa38": [
      8
    ],
    "a89a9b98": [
      11
    ],
    "5d915012": [
      8
    ],
    "53c5f278": [
      6
    ],
    "5d69ade9": [
      15
    ],
    "7132e043": [
      6
    ]
  }
}